{
  "GameDefaultString": "டெட்ரிஸ் போட்டி",
  "TitlePlaceHoler": "விளையாட்டின் தலைப்பை உள்ளிடவும்",
  "EndDate": "முடிவுத் தேதி",
  "Leaderboard": "லீடர்போர்டு",
  "LeaderBoardSetting": "லீடர்போர்டை எனக்கு மட்டுமே காண்பி",
  "LeaderBoardSettingSubstring": "ஸ்கோர் லீடர்போர்டைக் காண குழுவிலுள்ள அனைவரையும் அனுமதிக்க, தேர்வு நீக்கவும்",
  "AllowSingleTimePlay": "வீரர்களை ஒரு முறை மட்டுமே விளையாட அனுமதிக்கவும்",
  "AllowMultipleTimePlaySubstring": "வீரர்களை ஒரு முறை மட்டுமே விளையாட அனுமதிக்க தேர்வுநீக்கம் செய்யவும்",
  "AllowMultipleTimePlay": "வீரர்களை பல முறை விளையாட அனுமதிக்கவும்",
  "DueBy": "{0} அன்று கெடு",
  "Play": "விளையாடு",
  "SubmitScore": "ஸ்கோரை சமர்ப்பி",
  "GameExpired": "கேம் காலாவதியாகிவிட்டது...",
  "GameTitleErrorAlert": "தேவையானது",
  "HowToPlay": "எப்படி விளையாடுவது",
  "HowToPlayForMobile": "பலகையின் குறுக்கே தொகுதிகளை வைக்க இடது/வலது பக்கம் திரையை ஸ்வைப் செய்யவும். tbe தொகுதிகளை கடிகார திசையில் சுழற்றத் திரையில் தட்டவும். தொகுதிகளை விரைவாக கீழே நகர்த்த கீழே ஸ்வைப் செய்யவும். தெளிவான கோடுகளுக்கும் மதிப்பெண் புள்ளிகளுக்கும் தொகுதிகளை அருகில் வைக்கவும்",
  "HowToPlayForDesktop": "பலகை முழுவதும் தொகுதியை வைக்க இடது / வலது அம்புக்குறி விசைகளைப் பயன்படுத்தவும். தொகுதிகள் கடிகார திசையில் சுழற்ற மேல் அம்புக்குறி விசையைப் பயன்படுத்தவும். தொகுதிகளை விரைவாக கீழே நகர்த்த கீழ் அம்புக்குறி விசையைப் பயன்படுத்தவும். தெளிவான கோடுகள் மற்றும் மதிப்பெண் புள்ளிகளுக்கு அருகில் தொகுதிகள் வைக்கவும்",
  "DontShowTheGameInstruction": "விளையாட்டின் அறிவுறுத்தலை மீண்டும் எனக்கு காட்டாதே",
  "PlayButton": "விளையாடு",
  "Score": "ஸ்கோர்",
  "NoOneHasResponded": "இதுவரை யாரும் இந்த விளையாட்டை விளையாடவில்லை",
  "YouHaveNotResponded": "நீங்கள் இந்த விளையாட்டை விளையாடவில்லை",
  "OnlyOneAttemptError": "கேம் உருவாக்குநர் இந்தப் போட்டிக்காக ஒரே ஒரு முயற்சியை மட்டுமே அனுமதித்துள்ளார்",
  "YourScoreInScoreView": "உங்களுடைய ஸ்கோர்",
  "GameActiveString": "விளையாட்டு இன்னும் செயலில் உள்ளது ",
  "YourScoreInSummaryView": "உங்களுடைய ஸ்கோர்",
  "YourScoreOnCongratulationPage": "உங்கள் ஸ்கோர்: ",
  "LeaderboardInSummaryView": "லீடர்போர்டு",
  "LoadMore": "கூடுதல் ஸ்கோரை ஏற்று",
  "LoadLess": "குறைவாகக் காண்பி",
  "DueInYears": "{0} ஆண்டுகளில் கெடு",
  "DueInYear": "{0} ஆண்டில் கெடு",
  "DueInMonths": "{0} மாதங்களில் கெடு",
  "DueInMonth": "{0} மாதத்தில் கெடு",
  "DueInWeeks": "{0} வாரங்களில் கெடு",
  "DueInWeek": "{0} வாரத்தில் கெடு",
  "DueInDays": "{0} நாட்களில் கெடு",
  "DueInDay": "{0} நாளில் கெடு",
  "DueInHoursAndMinutes": "{0} மணிநேரம் {1} நிமிடங்களில் கெடு",
  "DueInHourAndMinutes": "{0} மணிநேரம் {1} நிமிடங்களில் கெடு",
  "DueInHoursAndMinute": "{0} மணிநேரம் {1} நிமிடத்தில் கெடு",
  "DueInHourAndMinute": "{0} மணிநேரம் {1} நிமிடத்தில் கெடு",
  "DueInHours": "{0} மணிநேரத்தில் கெடு",
  "DueInHour": "{0} மணிநேரத்தில் கெடு",
  "DueInMinutes": "{0} நிமிடங்களில் கெடு",
  "DueInMinute": "{0} நிமிடத்தில் கெடு",
  "SendGameRequest": "அனுப்பு",
  "BeTheFirstOneToRespond": "விளையாட முதல் நபராக இருக்கவும்",
  "OneResponded": "{0} விளையாடினார்",
  "TwoResponded": "{0}மற்றும்{1} விளையாடினர்.",
  "ThreeResponded": "{0}, {1} மற்றும் {2} இயக்கப்பட்டன.",
  "ThreeAndOneOtherResponded": "{0}, {1}, {2} மற்றும் மற்றொருவர் விளையாடியுள்ளனர்",
  "ThreeAndOthersResponded": "{0}, {1}, {2} மற்றும் {3}-ம் மற்றவர்களும் விளையாடியுள்ளனர்",
  "GenericError": "இந்தச் செயலியைத் தொடர்புகொள்வதில் சிக்கல் இருந்தது. சிறிது நேரம் கழித்து முயற்சி செய்யவும்.",
  "DialogTalkback": "{0} உரையாடல். {1}",
  "Close": "மூடு",
  "Cancel": "ரத்து",
  "Change": "மாற்று",
  "Confirm": "உறுதிசெய்",
  "dueBy": "கெடு:",
  "dueByDate": "{0} அன்று கெடு",
  "ChangeDueDate": "நிலுவை தேதியை மாற்று",
  "CloseGame": "போட்டியை மூடு",
  "DeleteGame": "போட்டியை நீக்கு",
  "CloseGameAlertText": "இந்தப் போட்டியை நிச்சயமாக மூட விரும்புகிறீர்களா?",
  "DeleteGameAlertText": "இந்தப் போட்டியை நீக்க விரும்புகிறீர்களா?",
  "SelectADate": "தேதியைத் தேர்ந்தெடுக்கவும்...",
  "SelectATime": "நேரத்தைத் தேர்ந்தெடுக்கவும்...",
  "SomethingWentWrong": "ஏதோ தவறாகிவிட்டது",
  "MoreOptions": "மேலும் விருப்பங்கள்",
  "DismissMenu": "நிராகரி மெனு",
  "$manifest.name": "டெட்ரிஸ் போட்டி",
  "$manifest.views.LaunchView.header": "புதிய போட்டியை உருவாக்கவும்",
  "$manifest.description": "டெட்ரிஸ் விளையாட்டின் போட்டியை நடத்துங்கள்",
  "$manifest.msTeamsProps.name.short": "டெட்ரிஸ் போட்டி",
  "$manifest.msTeamsProps.name.full": "டெட்ரிஸ் போட்டி",
  "$manifest.msTeamsProps.description.short": "டெட்ரிஸ் விளையாட்டின் போட்டியை நடத்துங்கள்",
  "$manifest.msTeamsProps.description.full": "டெட்ரிஸின் போட்டியை அரட்டையிலோ சேனலிலோ நடத்துங்கள். செய்தி எழுதுதல் பெட்டியின் கீழ் '…' இல் பயன்பாட்டைக் கண்டறியவும். உங்கள் போட்டிக்குத் தலைப்பை வழங்கவும், அதை உங்கள் அரட்டை அல்லது சேனலில் இடுகையிடவும். உங்கள் அணியுடன் மகிழுங்கள்!"
}